CHANGES.txt
CONTRIBUTORS.txt
COPYRIGHT.txt
LICENSE.txt
MANIFEST.in
README.txt
setup.py
docs/Makefile
docs/changes.rst
docs/conf.py
docs/index.rst
docs/.static/logo_hi.gif
docs/.static/repoze.css
src/repoze/__init__.py
src/repoze.filesafe_nfs.egg-info/PKG-INFO
src/repoze.filesafe_nfs.egg-info/SOURCES.txt
src/repoze.filesafe_nfs.egg-info/dependency_links.txt
src/repoze.filesafe_nfs.egg-info/entry_points.txt
src/repoze.filesafe_nfs.egg-info/namespace_packages.txt
src/repoze.filesafe_nfs.egg-info/not-zip-safe
src/repoze.filesafe_nfs.egg-info/requires.txt
src/repoze.filesafe_nfs.egg-info/top_level.txt
src/repoze/filesafe/__init__.py
src/repoze/filesafe/manager.py
src/repoze/filesafe/testing.py
src/repoze/filesafe/tests.py